latent_experiments.py
latent_experiments-0.0.7.dist-info/LICENSE
latent_experiments-0.0.7.dist-info/METADATA
latent_experiments-0.0.7.dist-info/WHEEL
latent_experiments-0.0.7.dist-info/top_level.txt
latent_experiments-0.0.7.dist-info/RECORD
